trader_okx/__init__.py
trader_okx-1.0.0.dev1.dist-info/METADATA
trader_okx-1.0.0.dev1.dist-info/WHEEL
trader_okx-1.0.0.dev1.dist-info/top_level.txt
trader_okx-1.0.0.dev1.dist-info/RECORD
